maker/__init__.py
maker/app.py
maker/commands.py
maker/config.py
maker/main.py
maker/screen.py
themes/__init__.py
themes/app.py
themes/main.py
themes/scr.py
tx_tools-0.2442.3.dist-info/METADATA
tx_tools-0.2442.3.dist-info/WHEEL
tx_tools-0.2442.3.dist-info/entry_points.txt
tx_tools-0.2442.3.dist-info/top_level.txt
tx_tools-0.2442.3.dist-info/RECORD
