Metadata-Version: 2.4
Name: tx_tools
Version: 0.2442.3
Summary: Tui tools
Author-email: Louis RIVIERE <louis@riviere.xyz>
Project-URL: pypi, https://pypi.org/project/tx-tools
Project-URL: repository, https://notabug.org/dugres/tx_tools
Keywords: util
Classifier: Development Status :: 3 - Alpha
Classifier: Programming Language :: Python :: 3
Classifier: Operating System :: POSIX :: Linux
Classifier: Environment :: Console
Classifier: Intended Audience :: Developers
Classifier: License :: OSI Approved :: MIT License
Requires-Python: >=3.8
Requires-Dist: pybrary
Requires-Dist: tx_widgets
